bword
