Metadata-Version: 1.0
Name: bword
Version: 0.10
Summary: a console translation dictionary used dict.baidu.com Api
Home-page: https://github.com/zhanghang-z
Author: zhanghang
Author-email: stevezhang@gmail.com
License: UNKNOWN
Keywords: python english translation dictionary terminal
Platform: UNKNOWN
